moxn_models/__init__.py
moxn_models/base.py
moxn_models/content.py
moxn_models/core.py
moxn_models/exceptions.py
moxn_models/py.typed
moxn_models/schema.py
moxn_models/telemetry.py
moxn_models/utils.py
moxn_models/blocks/base.py
moxn_models/blocks/content_block.py
moxn_models/blocks/context.py
moxn_models/blocks/document.py
moxn_models/blocks/image.py
moxn_models/blocks/signed.py
moxn_models/blocks/text.py
moxn_models/blocks/tool.py
moxn_models/blocks/variable.py
moxn_models/type_aliases/anthropic.py
moxn_models/type_aliases/google.py
moxn_models/type_aliases/openai_chat.py
moxn_models/type_aliases/provider.py
moxn_models-0.0.6.26.dist-info/METADATA
moxn_models-0.0.6.26.dist-info/WHEEL
moxn_models-0.0.6.26.dist-info/RECORD
