Metadata-Version: 2.4
Name: moxn-models
Version: 0.0.6.26
Summary: Shared DTOs for the Moxn SDK and API
Author-email: Mark Weiss <mark@moxn.dev>
Requires-Python: >=3.11
Requires-Dist: pydantic>=2.9
